nodens/gateway/__init__.py
nodens/gateway/__main__.py
nodens/gateway/nodens_fns.py
nodens/gateway/nodens_insight_hub.py
nodens/gateway/nodens_mesh.py
nodens/gateway/nodens_serv.py
nodens/gateway/nodens_thingsboard.py
nodens_gateway-25.3.1.dist-info/licenses/LICENSE
nodens_gateway-25.3.1.dist-info/METADATA
nodens_gateway-25.3.1.dist-info/PKG-INFO-Hawk
nodens_gateway-25.3.1.dist-info/WHEEL
nodens_gateway-25.3.1.dist-info/entry_points.txt
nodens_gateway-25.3.1.dist-info/requires-Hawk.txt
nodens_gateway-25.3.1.dist-info/top_level.txt
nodens_gateway-25.3.1.dist-info/RECORD
