Metadata-Version: 2.4
Name: nodens-gateway
Version: 25.3.1
Summary: Run the NodeNs gateway
Author-email: Khalid Z Rajab <khalid@nodens.eu>
License-Expression: MIT
Project-URL: Homepage, https://www.nodens.eu
Keywords: nodens,gateway,radar
Classifier: Programming Language :: Python
Classifier: Programming Language :: Python :: 3
Requires-Python: >=3.7
License-File: LICENSE
Requires-Dist: paho-mqtt==1.6.1
Requires-Dist: tomli; python_version < "3.11"
Requires-Dist: pyyaml
Requires-Dist: numpy
Requires-Dist: platformdirs
Dynamic: license-file
